lavague/contexts/fireworks/__init__.py
lavague/contexts/fireworks/base.py
lavague/contexts/fireworks/firectl
lavague_contexts_fireworks-0.0.3.dist-info/METADATA
lavague_contexts_fireworks-0.0.3.dist-info/WHEEL
lavague_contexts_fireworks-0.0.3.dist-info/RECORD
